fedbase/__init__.py
fedbase/baselines/__init__.py
fedbase/baselines/central.py
fedbase/baselines/ditto.py
fedbase/baselines/fedavg.py
fedbase/baselines/fedavg_ensemble.py
fedbase/baselines/fedprox.py
fedbase/baselines/fedprox_ensemble.py
fedbase/baselines/fesem.py
fedbase/baselines/fesem_cam.py
fedbase/baselines/fesem_con.py
fedbase/baselines/ifca.py
fedbase/baselines/ifca_cam.py
fedbase/baselines/ifca_con.py
fedbase/baselines/local.py
fedbase/baselines/wecfl.py
fedbase/baselines/wecfl_cam.py
fedbase/baselines/wecfl_con.py
fedbase/model/__init__.py
fedbase/model/model.py
fedbase/model/resnet.py
fedbase/nodes/__init__.py
fedbase/nodes/node.py
fedbase/server/__init__.py
fedbase/server/server.py
fedbase/utils/__init__.py
fedbase/utils/data_loader.py
fedbase/utils/femnist.py
fedbase/utils/model_utils.py
fedbase/utils/tools.py
fedbase/utils/visualize.py
fedbase-0.10.3.dist-info/LICENSE
fedbase-0.10.3.dist-info/METADATA
fedbase-0.10.3.dist-info/WHEEL
fedbase-0.10.3.dist-info/top_level.txt
fedbase-0.10.3.dist-info/RECORD
