Metadata-Version: 2.1
Name: fedbase
Version: 0.10.3
Summary: An easy, silly, DIY Federated Learning framework with many baselines for individual researchers.
Home-page: https://github.com/jie-ma-ai/FedBase
Author: Jie MA
Author-email: ustcmj@gmail.com
License: UNKNOWN
Platform: UNKNOWN
Classifier: Programming Language :: Python :: 3
Classifier: License :: OSI Approved :: MIT License
Classifier: Operating System :: OS Independent
License-File: LICENSE
